LittlePaimon/__init__.py
LittlePaimon/config/__init__.py
LittlePaimon/config/command/__init__.py
LittlePaimon/config/config/manage.py
LittlePaimon/config/config/model.py
LittlePaimon/config/data/alias.json
LittlePaimon/config/data/artifact.json
LittlePaimon/config/data/ban_word.txt
LittlePaimon/config/data/genshin_info.json
LittlePaimon/config/data/prop.json
LittlePaimon/config/data/role_skill.json
LittlePaimon/config/data/role_talent.json
LittlePaimon/config/data/roles_data.json
LittlePaimon/config/data/score.json
LittlePaimon/config/data/upheaval.json
LittlePaimon/config/data/weapon.json
LittlePaimon/config/data/类型.json
LittlePaimon/config/plugin/manage.py
LittlePaimon/config/plugin/model.py
LittlePaimon/database/__init__.py
LittlePaimon/database/models/__init__.py
LittlePaimon/database/models/abyss_info.py
LittlePaimon/database/models/character.py
LittlePaimon/database/models/cookie.py
LittlePaimon/database/models/genshin_voice.py
LittlePaimon/database/models/manage.py
LittlePaimon/database/models/memory_db.py
LittlePaimon/database/models/other.py
LittlePaimon/database/models/player_info.py
LittlePaimon/database/models/subscription.py
LittlePaimon/plugins/Genshin_Calendar/__init__.py
LittlePaimon/plugins/Genshin_Calendar/event.py
LittlePaimon/plugins/Genshin_Calendar/generate.py
LittlePaimon/plugins/Genshin_Calendar/template/calendar.html
LittlePaimon/plugins/Genshin_Calendar/template/index.css
LittlePaimon/plugins/Genshin_Calendar/template/iview.css
LittlePaimon/plugins/Genshin_Calendar/template/normalize.css
LittlePaimon/plugins/Genshin_Calendar/template/sy.jpg
LittlePaimon/plugins/Genshin_Voice/__init__.py
LittlePaimon/plugins/Genshin_Voice/draw.py
LittlePaimon/plugins/Genshin_Voice/handler.py
LittlePaimon/plugins/Genshin_Voice/resources.py
LittlePaimon/plugins/Learning_Chat/__init__.py
LittlePaimon/plugins/Learning_Chat/config.py
LittlePaimon/plugins/Learning_Chat/genshin_word.txt
LittlePaimon/plugins/Learning_Chat/handler.py
mhmzx_little_paimon-3.0.20.dist-info/LICENSE
mhmzx_little_paimon-3.0.20.dist-info/METADATA
mhmzx_little_paimon-3.0.20.dist-info/WHEEL
mhmzx_little_paimon-3.0.20.dist-info/RECORD
