Metadata-Version: 2.1
Name: mhmzx-little-paimon
Version: 3.0.20
Summary: （非官方）小派蒙！原神qq群机器人，基于NoneBot2的UID查询、抽卡导出分析、模拟抽卡、实时便签、札记等多功能小助手。
License: AGPL
Author: Madray Haven
Author-email: sgpublic2002@gmail.com
Requires-Python: >=3.8,<4.0
Classifier: License :: Other/Proprietary License
Classifier: Programming Language :: Python :: 3
Classifier: Programming Language :: Python :: 3.8
Classifier: Programming Language :: Python :: 3.9
Classifier: Programming Language :: Python :: 3.10
Classifier: Programming Language :: Python :: 3.11
Classifier: Programming Language :: Python :: 3.12
Requires-Dist: Pillow (>=9.1.0,<10.0.0)
Requires-Dist: amis-python (>=1.0.5,<2.0.0)
Requires-Dist: beautifulsoup4 (>=4.10.0,<5.0.0)
Requires-Dist: expandvars (>=0.9.0,<0.10.0)
Requires-Dist: gitpython (>=3.1.27,<4.0.0)
Requires-Dist: httpx (>=0.23.0,<0.24.0)
Requires-Dist: jieba (>=0.42.1,<0.43.0)
Requires-Dist: lxml (>=4.8.0,<5.0.0)
Requires-Dist: matplotlib (>=3.5.1,<4.0.0)
Requires-Dist: nonebot-adapter-onebot (>=2.1,<3.0)
Requires-Dist: nonebot-plugin-apscheduler (>=0.2.0,<0.3.0)
Requires-Dist: nonebot2[fastapi] (>=2.0.0-rc.2,<3.0.0)
Requires-Dist: playwright (>=1.27.1,<2.0.0)
Requires-Dist: psutil (>=5.9.3,<6.0.0)
Requires-Dist: pypinyin (>=0.47.1,<0.48.0)
Requires-Dist: python-jose (>=3.3.0,<4.0.0)
Requires-Dist: qrcode (>=7.3.1,<8.0.0)
Requires-Dist: ruamel.yaml (>=0.17.21,<0.18.0)
Requires-Dist: scikit-learn (>=1.1.2,<2.0.0)
Requires-Dist: scipy (>=1.9.1,<2.0.0)
Requires-Dist: shapely (>=1.8.4,<2.0.0)
Requires-Dist: tortoise-orm (>=0.19.2,<0.20.0)
Requires-Dist: tqdm (>=4.64.0,<5.0.0)
Requires-Dist: ujson (>=5.4.0,<6.0.0)
